{
	"resultList": [
		[
			{
				"onoff": "1",
				"from": "명지대학교 인문캠퍼스",
				"to": "숙명여자대학교",
				"from_id": "13228",
				"to_id": "02122",
				"busRouteId": "100100340",
				"busNm": "7021",
				"stId": "112000145",
				"ord": "21",
				"stNm": "백련시장",
				"arsId": "13228"
			},
			{
				"onoff": "2",
				"from": "명지대학교 인문캠퍼스",
				"to": "숙명여자대학교",
				"from_id": "13228",
				"to_id": "02122",
				"busRouteId": "100100340",
				"busNm": "7021",
				"stId": "101000027",
				"ord": "38",
				"stNm": "숭례문",
				"arsId": "02122"
			}
		],
		[
			{
				"onoff": "1",
				"from": "명지대학교 인문캠퍼스",
				"to": "숙명여자대학교",
				"from_id": "02118",
				"to_id": "03234",
				"busRouteId": "100100597",
				"busNm": "405",
				"stId": "101000023",
				"ord": "49",
				"stNm": "숭례문",
				"arsId": "02118"
			},
			{
			}
		],
		[
			{
				"onoff": "1",
				"from": "명지대학교 인문캠퍼스",
				"to": "숙명여자대학교",
				"from_id": "13228",
				"to_id": "02122",
				"busRouteId": "100100337",
				"busNm": "7017",
				"stId": "112000145",
				"ord": "20",
				"stNm": "백련시장",
				"arsId": "13228"
			},
			{
				"onoff": "2",
				"from": "명지대학교 인문캠퍼스",
				"to": "숙명여자대학교",
				"from_id": "13228",
				"to_id": "02122",
				"busRouteId": "100100337",
				"busNm": "7017",
				"stId": "101000027",
				"ord": "40",
				"stNm": "숭례문",
				"arsId": "02122"
			}
		],
		[
			{
				"onoff": "1",
				"from": "명지대학교 인문캠퍼스",
				"to": "숙명여자대학교",
				"from_id": "02118",
				"to_id": "03234",
				"busRouteId": "100100597",
				"busNm": "405",
				"stId": "101000023",
				"ord": "49",
				"stNm": "숭례문",
				"arsId": "02118"
			},
			{
			}
		],
		[
			{
				"onoff": "1",
				"from": "명지대학교 인문캠퍼스",
				"to": "숙명여자대학교",
				"from_id": "13217",
				"to_id": "01188",
				"busRouteId": "100100338",
				"busNm": "7018",
				"stId": "112000134",
				"ord": "11",
				"stNm": "명지대입구.서울무용센터",
				"arsId": "13217"
			},
			{
				"onoff": "2",
				"from": "명지대학교 인문캠퍼스",
				"to": "숙명여자대학교",
				"from_id": "13217",
				"to_id": "01188",
				"busRouteId": "100100338",
				"busNm": "7018",
				"stId": "100000092",
				"ord": "30",
				"stNm": "종로1가",
				"arsId": "01188"
			}
		],
		[
			{
				"onoff": "1",
				"from": "명지대학교 인문캠퍼스",
				"to": "숙명여자대학교",
				"from_id": "01188",
				"to_id": "03234",
				"busRouteId": "100100597",
				"busNm": "405",
				"stId": "100000092",
				"ord": "45",
				"stNm": "종로1가",
				"arsId": "01188"
			},
			{
			}
		],
		[
			{
				"onoff": "1",
				"from": "명지대학교 인문캠퍼스",
				"to": "숙명여자대학교",
				"from_id": "13219",
				"to_id": "02134",
				"busRouteId": "100100339",
				"busNm": "7019",
				"stId": "112000136",
				"ord": "17",
				"stNm": "명지중고등학교",
				"arsId": "13219"
			},
			{
				"onoff": "2",
				"from": "명지대학교 인문캠퍼스",
				"to": "숙명여자대학교",
				"from_id": "13219",
				"to_id": "02134",
				"busRouteId": "100100339",
				"busNm": "7019",
				"stId": "101000037",
				"ord": "45",
				"stNm": "서소문",
				"arsId": "02134"
			}
		],
		[
			{
				"onoff": "1",
				"from": "명지대학교 인문캠퍼스",
				"to": "숙명여자대학교",
				"from_id": "02128",
				"to_id": "03234",
				"busRouteId": "100100597",
				"busNm": "405",
				"stId": "101000033",
				"ord": "43",
				"stNm": "시청앞",
				"arsId": "02128"
			},
			{
			}
		]
	]
}