{
	"resultList": [
		[
			{
				"onoff": "1",
				"from": "삼육대학교",
				"to": "한국예술종합학교",
				"from_id": "11153",
				"to_id": "11284",
				"busRouteId": "100100165",
				"busNm": "1155",
				"stId": "110000053",
				"ord": "25",
				"stNm": "한국체육과학연구원",
				"arsId": "11153"
			},
			{
				"onoff": "2",
				"from": "삼육대학교",
				"to": "한국예술종합학교",
				"from_id": "11153",
				"to_id": "11284",
				"busRouteId": "100100165",
				"busNm": "1155",
				"stId": "110000184",
				"ord": "37",
				"stNm": "석계역2번출구",
				"arsId": "11284"
			}
		],
		[
			{
			},
			{
				"onoff": "2",
				"from": "삼육대학교",
				"to": "한국예술종합학교",
				"from_id": "11283",
				"to_id": "08142",
				"busRouteId": "100100035",
				"busNm": "163",
				"stId": "107000052",
				"ord": "10",
				"stNm": "돌곶이역",
				"arsId": "08142"
			}
		],
		[
			{
				"onoff": "1",
				"from": "삼육대학교",
				"to": "한국예술종합학교",
				"from_id": "11153",
				"to_id": "11284",
				"busRouteId": "100100166",
				"busNm": "1156",
				"stId": "110000053",
				"ord": "21",
				"stNm": "한국체육과학연구원",
				"arsId": "11153"
			},
			{
				"onoff": "2",
				"from": "삼육대학교",
				"to": "한국예술종합학교",
				"from_id": "11153",
				"to_id": "11284",
				"busRouteId": "100100166",
				"busNm": "1156",
				"stId": "110000184",
				"ord": "33",
				"stNm": "석계역2번출구",
				"arsId": "11284"
			}
		],
		[
			{
			},
			{
				"onoff": "2",
				"from": "삼육대학교",
				"to": "한국예술종합학교",
				"from_id": "11283",
				"to_id": "08142",
				"busRouteId": "100100035",
				"busNm": "163",
				"stId": "107000052",
				"ord": "10",
				"stNm": "돌곶이역",
				"arsId": "08142"
			}
		],
		[
			{
				"onoff": "1",
				"from": "삼육대학교",
				"to": "한국예술종합학교",
				"from_id": "11153",
				"to_id": "11312",
				"busRouteId": "100100165",
				"busNm": "1155",
				"stId": "110000053",
				"ord": "25",
				"stNm": "한국체육과학연구원",
				"arsId": "11153"
			},
			{
				"onoff": "2",
				"from": "삼육대학교",
				"to": "한국예술종합학교",
				"from_id": "11153",
				"to_id": "11312",
				"busRouteId": "100100165",
				"busNm": "1155",
				"stId": "110000212",
				"ord": "36",
				"stNm": "한진한화그랑빌아파트",
				"arsId": "11312"
			}
		],
		[
			{
				"onoff": "1",
				"from": "삼육대학교",
				"to": "한국예술종합학교",
				"from_id": "11312",
				"to_id": "08211",
				"busRouteId": "100100179",
				"busNm": "1222",
				"stId": "110000212",
				"ord": "8",
				"stNm": "한진한화그랑빌아파트",
				"arsId": "11312"
			},
			{
				"onoff": "2",
				"from": "삼육대학교",
				"to": "한국예술종합학교",
				"from_id": "11312",
				"to_id": "08211",
				"busRouteId": "100100179",
				"busNm": "1222",
				"stId": "107000121",
				"ord": "14",
				"stNm": "석관시장",
				"arsId": "08211"
			}
		],
		[
			{
				"onoff": "1",
				"from": "삼육대학교",
				"to": "한국예술종합학교",
				"from_id": "11153",
				"to_id": "11312",
				"busRouteId": "100100166",
				"busNm": "1156",
				"stId": "110000053",
				"ord": "21",
				"stNm": "한국체육과학연구원",
				"arsId": "11153"
			},
			{
				"onoff": "2",
				"from": "삼육대학교",
				"to": "한국예술종합학교",
				"from_id": "11153",
				"to_id": "11312",
				"busRouteId": "100100166",
				"busNm": "1156",
				"stId": "110000212",
				"ord": "32",
				"stNm": "한진한화그랑빌아파트",
				"arsId": "11312"
			}
		],
		[
			{
				"onoff": "1",
				"from": "삼육대학교",
				"to": "한국예술종합학교",
				"from_id": "11312",
				"to_id": "08211",
				"busRouteId": "100100179",
				"busNm": "1222",
				"stId": "110000212",
				"ord": "8",
				"stNm": "한진한화그랑빌아파트",
				"arsId": "11312"
			},
			{
				"onoff": "2",
				"from": "삼육대학교",
				"to": "한국예술종합학교",
				"from_id": "11312",
				"to_id": "08211",
				"busRouteId": "100100179",
				"busNm": "1222",
				"stId": "107000121",
				"ord": "14",
				"stNm": "석관시장",
				"arsId": "08211"
			}
		],
		[
			{
				"onoff": "1",
				"from": "삼육대학교",
				"to": "한국예술종합학교",
				"from_id": "11153",
				"to_id": "11284",
				"busRouteId": "100100166",
				"busNm": "1156",
				"stId": "110000053",
				"ord": "21",
				"stNm": "한국체육과학연구원",
				"arsId": "11153"
			},
			{
				"onoff": "2",
				"from": "삼육대학교",
				"to": "한국예술종합학교",
				"from_id": "11153",
				"to_id": "11284",
				"busRouteId": "100100166",
				"busNm": "1156",
				"stId": "110000184",
				"ord": "33",
				"stNm": "석계역2번출구",
				"arsId": "11284"
			}
		],
		[
			{
				"onoff": "1",
				"from": "삼육대학교",
				"to": "한국예술종합학교",
				"from_id": "11457",
				"to_id": "08211",
				"busRouteId": "100100043",
				"busNm": "261",
				"stId": "110000356",
				"ord": "3",
				"stNm": "석계역1번출구",
				"arsId": "11457"
			},
			{
				"onoff": "2",
				"from": "삼육대학교",
				"to": "한국예술종합학교",
				"from_id": "11457",
				"to_id": "08211",
				"busRouteId": "100100043",
				"busNm": "261",
				"stId": "107000121",
				"ord": "18",
				"stNm": "석관시장",
				"arsId": "08211"
			}
		]
	]
}