{
	"resultList": [
		[
			{
				"onoff": "1",
				"from": "광운대학교",
				"to": "서울대학교 관악캠퍼스",
				"from_id": "11476",
				"to_id": "01291",
				"busRouteId": "100100035",
				"busNm": "163",
				"stId": "110000375",
				"ord": "6",
				"stNm": "물류센타",
				"arsId": "11476"
			},
			{
				"onoff": "2",
				"from": "광운대학교",
				"to": "서울대학교 관악캠퍼스",
				"from_id": "11476",
				"to_id": "01291",
				"busRouteId": "100100035",
				"busNm": "163",
				"stId": "100000192",
				"ord": "34",
				"stNm": "청계2가.삼일교",
				"arsId": "01291"
			}
		],
		[
			{
				"onoff": "1",
				"from": "광운대학교",
				"to": "서울대학교 관악캠퍼스",
				"from_id": "01185",
				"to_id": "21127",
				"busRouteId": "100100077",
				"busNm": "501",
				"stId": "100000089",
				"ord": "29",
				"stNm": "종로2가",
				"arsId": "01185"
			},
			{
				"onoff": "2",
				"from": "광운대학교",
				"to": "서울대학교 관악캠퍼스",
				"from_id": "01185",
				"to_id": "21127",
				"busRouteId": "100100077",
				"busNm": "501",
				"stId": "120000028",
				"ord": "55",
				"stNm": "서울대학교",
				"arsId": "21127"
			}
		],
		[
			{
				"onoff": "1",
				"from": "광운대학교",
				"to": "서울대학교 관악캠퍼스",
				"from_id": "11465",
				"to_id": "02158",
				"busRouteId": "100100043",
				"busNm": "261",
				"stId": "110000364",
				"ord": "10",
				"stNm": "벼루말교",
				"arsId": "11465"
			},
			{
				"onoff": "2",
				"from": "광운대학교",
				"to": "서울대학교 관악캠퍼스",
				"from_id": "11465",
				"to_id": "02158",
				"busRouteId": "100100043",
				"busNm": "261",
				"stId": "101000059",
				"ord": "42",
				"stNm": "을지로2가.기업은행본점.서울노동청",
				"arsId": "02158"
			}
		],
		[
			{
				"onoff": "1",
				"from": "광운대학교",
				"to": "서울대학교 관악캠퍼스",
				"from_id": "02158",
				"to_id": "21127",
				"busRouteId": "100100077",
				"busNm": "501",
				"stId": "101000059",
				"ord": "30",
				"stNm": "을지로2가.기업은행본점.서울노동청",
				"arsId": "02158"
			},
			{
				"onoff": "2",
				"from": "광운대학교",
				"to": "서울대학교 관악캠퍼스",
				"from_id": "02158",
				"to_id": "21127",
				"busRouteId": "100100077",
				"busNm": "501",
				"stId": "120000028",
				"ord": "55",
				"stNm": "서울대학교",
				"arsId": "21127"
			}
		],
		[
			{
				"onoff": "1",
				"from": "광운대학교",
				"to": "서울대학교 관악캠퍼스",
				"from_id": "11476",
				"to_id": "02246",
				"busRouteId": "100100035",
				"busNm": "163",
				"stId": "110000375",
				"ord": "6",
				"stNm": "물류센타",
				"arsId": "11476"
			},
			{
				"onoff": "2",
				"from": "광운대학교",
				"to": "서울대학교 관악캠퍼스",
				"from_id": "11476",
				"to_id": "02246",
				"busRouteId": "100100035",
				"busNm": "163",
				"stId": "101000141",
				"ord": "36",
				"stNm": "을지로입구역.광교",
				"arsId": "02246"
			}
		],
		[
			{
				"onoff": "1",
				"from": "광운대학교",
				"to": "서울대학교 관악캠퍼스",
				"from_id": "02246",
				"to_id": "21127",
				"busRouteId": "100100081",
				"busNm": "506",
				"stId": "101000141",
				"ord": "48",
				"stNm": "을지로입구역.광교",
				"arsId": "02246"
			},
			{
				"onoff": "2",
				"from": "광운대학교",
				"to": "서울대학교 관악캠퍼스",
				"from_id": "02246",
				"to_id": "21127",
				"busRouteId": "100100081",
				"busNm": "506",
				"stId": "120000028",
				"ord": "98",
				"stNm": "서울대학교",
				"arsId": "21127"
			}
		],
		[
			{
				"onoff": "1",
				"from": "광운대학교",
				"to": "서울대학교 관악캠퍼스",
				"from_id": "11465",
				"to_id": "02140",
				"busRouteId": "100100043",
				"busNm": "261",
				"stId": "110000364",
				"ord": "10",
				"stNm": "벼루말교",
				"arsId": "11465"
			},
			{
				"onoff": "2",
				"from": "광운대학교",
				"to": "서울대학교 관악캠퍼스",
				"from_id": "11465",
				"to_id": "02140",
				"busRouteId": "100100043",
				"busNm": "261",
				"stId": "101000041",
				"ord": "43",
				"stNm": "롯데백화점",
				"arsId": "02140"
			}
		],
		[
			{
				"onoff": "1",
				"from": "광운대학교",
				"to": "서울대학교 관악캠퍼스",
				"from_id": "02141",
				"to_id": "21127",
				"busRouteId": "100100081",
				"busNm": "506",
				"stId": "101000042",
				"ord": "49",
				"stNm": "해운센터.롯데영프라자",
				"arsId": "02141"
			},
			{
				"onoff": "2",
				"from": "광운대학교",
				"to": "서울대학교 관악캠퍼스",
				"from_id": "02141",
				"to_id": "21127",
				"busRouteId": "100100081",
				"busNm": "506",
				"stId": "120000028",
				"ord": "98",
				"stNm": "서울대학교",
				"arsId": "21127"
			}
		],
		[
			{
				"onoff": "1",
				"from": "광운대학교",
				"to": "서울대학교 관악캠퍼스",
				"from_id": "11465",
				"to_id": "19153",
				"busRouteId": "100100043",
				"busNm": "261",
				"stId": "110000364",
				"ord": "10",
				"stNm": "벼루말교",
				"arsId": "11465"
			},
			{
				"onoff": "2",
				"from": "광운대학교",
				"to": "서울대학교 관악캠퍼스",
				"from_id": "11465",
				"to_id": "19153",
				"busRouteId": "100100043",
				"busNm": "261",
				"stId": "118000068",
				"ord": "59",
				"stNm": "지적공사",
				"arsId": "19153"
			}
		],
		[
			{
				"onoff": "1",
				"from": "광운대학교",
				"to": "서울대학교 관악캠퍼스",
				"from_id": "19154",
				"to_id": "21127",
				"busRouteId": "100100293",
				"busNm": "6513",
				"stId": "118000069",
				"ord": "23",
				"stNm": "지적공사",
				"arsId": "19154"
			},
			{
				"onoff": "2",
				"from": "광운대학교",
				"to": "서울대학교 관악캠퍼스",
				"from_id": "19154",
				"to_id": "21127",
				"busRouteId": "100100293",
				"busNm": "6513",
				"stId": "120000028",
				"ord": "40",
				"stNm": "서울대학교",
				"arsId": "21127"
			}
		]
	]
}