{
	"resultList": [
		[
			{
				"onoff": "1",
				"from": "광운대학교",
				"to": "이화여자대학교",
				"from_id": "08218",
				"to_id": "13025",
				"busRouteId": "100100037",
				"busNm": "172",
				"stId": "107000128",
				"ord": "9",
				"stNm": "광운초교앞",
				"arsId": "08218"
			},
			{
				"onoff": "2",
				"from": "광운대학교",
				"to": "이화여자대학교",
				"from_id": "08218",
				"to_id": "13025",
				"busRouteId": "100100037",
				"busNm": "172",
				"stId": "113000411",
				"ord": "35",
				"stNm": "이대역",
				"arsId": "13025"
			}
		],
		[
			{
				"onoff": "1",
				"from": "광운대학교",
				"to": "이화여자대학교",
				"from_id": "11278",
				"to_id": "14209",
				"busRouteId": "100100035",
				"busNm": "163",
				"stId": "110000178",
				"ord": "4",
				"stNm": "광운대역",
				"arsId": "11278"
			},
			{
				"onoff": "2",
				"from": "광운대학교",
				"to": "이화여자대학교",
				"from_id": "11278",
				"to_id": "14209",
				"busRouteId": "100100035",
				"busNm": "163",
				"stId": "113000118",
				"ord": "52",
				"stNm": "이화여대입구",
				"arsId": "14209"
			}
		]
	]
}