{
	"resultList": [
		[
			{
				"onoff": "1",
				"from": "한국성서대학교",
				"to": "이화여자대학교",
				"from_id": "11366",
				"to_id": "11447",
				"busRouteId": "100100010",
				"busNm": "105",
				"stId": "110000265",
				"ord": "8",
				"stNm": "중계역",
				"arsId": "11366"
			},
			{
				"onoff": "2",
				"from": "한국성서대학교",
				"to": "이화여자대학교",
				"from_id": "11366",
				"to_id": "11447",
				"busRouteId": "100100010",
				"busNm": "105",
				"stId": "110000346",
				"ord": "10",
				"stNm": "하계역",
				"arsId": "11447"
			}
		],
		[
			{
				"onoff": "1",
				"from": "한국성서대학교",
				"to": "이화여자대학교",
				"from_id": "11454",
				"to_id": "13025",
				"busRouteId": "100100037",
				"busNm": "172",
				"stId": "110000353",
				"ord": "3",
				"stNm": "하계우성아파트",
				"arsId": "11454"
			},
			{
				"onoff": "2",
				"from": "한국성서대학교",
				"to": "이화여자대학교",
				"from_id": "11454",
				"to_id": "13025",
				"busRouteId": "100100037",
				"busNm": "172",
				"stId": "113000411",
				"ord": "35",
				"stNm": "이대역",
				"arsId": "13025"
			}
		],
		[
			{
				"onoff": "1",
				"from": "한국성서대학교",
				"to": "이화여자대학교",
				"from_id": "11366",
				"to_id": "11447",
				"busRouteId": "100100025",
				"busNm": "146",
				"stId": "110000265",
				"ord": "22",
				"stNm": "중계역",
				"arsId": "11366"
			},
			{
				"onoff": "2",
				"from": "한국성서대학교",
				"to": "이화여자대학교",
				"from_id": "11366",
				"to_id": "11447",
				"busRouteId": "100100025",
				"busNm": "146",
				"stId": "110000346",
				"ord": "24",
				"stNm": "하계역",
				"arsId": "11447"
			}
		],
		[
			{
				"onoff": "1",
				"from": "한국성서대학교",
				"to": "이화여자대학교",
				"from_id": "11454",
				"to_id": "13025",
				"busRouteId": "100100037",
				"busNm": "172",
				"stId": "110000353",
				"ord": "3",
				"stNm": "하계우성아파트",
				"arsId": "11454"
			},
			{
				"onoff": "2",
				"from": "한국성서대학교",
				"to": "이화여자대학교",
				"from_id": "11454",
				"to_id": "13025",
				"busRouteId": "100100037",
				"busNm": "172",
				"stId": "113000411",
				"ord": "35",
				"stNm": "이대역",
				"arsId": "13025"
			}
		],
		[
			{
				"onoff": "1",
				"from": "한국성서대학교",
				"to": "이화여자대학교",
				"from_id": "11366",
				"to_id": "11447",
				"busRouteId": "100100150",
				"busNm": "1135",
				"stId": "110000265",
				"ord": "34",
				"stNm": "중계역",
				"arsId": "11366"
			},
			{
				"onoff": "2",
				"from": "한국성서대학교",
				"to": "이화여자대학교",
				"from_id": "11366",
				"to_id": "11447",
				"busRouteId": "100100150",
				"busNm": "1135",
				"stId": "110000346",
				"ord": "36",
				"stNm": "하계역",
				"arsId": "11447"
			}
		],
		[
			{
				"onoff": "1",
				"from": "한국성서대학교",
				"to": "이화여자대학교",
				"from_id": "11454",
				"to_id": "13025",
				"busRouteId": "100100037",
				"busNm": "172",
				"stId": "110000353",
				"ord": "3",
				"stNm": "하계우성아파트",
				"arsId": "11454"
			},
			{
				"onoff": "2",
				"from": "한국성서대학교",
				"to": "이화여자대학교",
				"from_id": "11454",
				"to_id": "13025",
				"busRouteId": "100100037",
				"busNm": "172",
				"stId": "113000411",
				"ord": "35",
				"stNm": "이대역",
				"arsId": "13025"
			}
		],
		[
			{
				"onoff": "1",
				"from": "한국성서대학교",
				"to": "이화여자대학교",
				"from_id": "11366",
				"to_id": "11447",
				"busRouteId": "100100152",
				"busNm": "1137",
				"stId": "110000265",
				"ord": "16",
				"stNm": "중계역",
				"arsId": "11366"
			},
			{
				"onoff": "2",
				"from": "한국성서대학교",
				"to": "이화여자대학교",
				"from_id": "11366",
				"to_id": "11447",
				"busRouteId": "100100152",
				"busNm": "1137",
				"stId": "110000346",
				"ord": "18",
				"stNm": "하계역",
				"arsId": "11447"
			}
		],
		[
			{
				"onoff": "1",
				"from": "한국성서대학교",
				"to": "이화여자대학교",
				"from_id": "11454",
				"to_id": "13025",
				"busRouteId": "100100037",
				"busNm": "172",
				"stId": "110000353",
				"ord": "3",
				"stNm": "하계우성아파트",
				"arsId": "11454"
			},
			{
				"onoff": "2",
				"from": "한국성서대학교",
				"to": "이화여자대학교",
				"from_id": "11454",
				"to_id": "13025",
				"busRouteId": "100100037",
				"busNm": "172",
				"stId": "113000411",
				"ord": "35",
				"stNm": "이대역",
				"arsId": "13025"
			}
		],
		[
			{
				"onoff": "1",
				"from": "한국성서대학교",
				"to": "이화여자대학교",
				"from_id": "11366",
				"to_id": "11447",
				"busRouteId": "100100155",
				"busNm": "1140",
				"stId": "110000265",
				"ord": "35",
				"stNm": "중계역",
				"arsId": "11366"
			},
			{
				"onoff": "2",
				"from": "한국성서대학교",
				"to": "이화여자대학교",
				"from_id": "11366",
				"to_id": "11447",
				"busRouteId": "100100155",
				"busNm": "1140",
				"stId": "110000346",
				"ord": "37",
				"stNm": "하계역",
				"arsId": "11447"
			}
		],
		[
			{
				"onoff": "1",
				"from": "한국성서대학교",
				"to": "이화여자대학교",
				"from_id": "11454",
				"to_id": "13025",
				"busRouteId": "100100037",
				"busNm": "172",
				"stId": "110000353",
				"ord": "3",
				"stNm": "하계우성아파트",
				"arsId": "11454"
			},
			{
				"onoff": "2",
				"from": "한국성서대학교",
				"to": "이화여자대학교",
				"from_id": "11454",
				"to_id": "13025",
				"busRouteId": "100100037",
				"busNm": "172",
				"stId": "113000411",
				"ord": "35",
				"stNm": "이대역",
				"arsId": "13025"
			}
		]
	]
}