{
	"resultList": [
		[
			{
				"onoff": "1",
				"from": "서울대학교 관악캠퍼스",
				"to": "숙명여자대학교",
				"from_id": "21128",
				"to_id": "03003",
				"busRouteId": "100100077",
				"busNm": "501",
				"stId": "120000029",
				"ord": "4",
				"stNm": "서울대학교",
				"arsId": "21128"
			},
			{
				"onoff": "2",
				"from": "서울대학교 관악캠퍼스",
				"to": "숙명여자대학교",
				"from_id": "21128",
				"to_id": "03003",
				"busRouteId": "100100077",
				"busNm": "501",
				"stId": "102000003",
				"ord": "19",
				"stNm": "신용산역",
				"arsId": "03003"
			}
		],
		[
			{
			},
			{
			}
		],
		[
			{
				"onoff": "1",
				"from": "서울대학교 관악캠퍼스",
				"to": "숙명여자대학교",
				"from_id": "21128",
				"to_id": "03003",
				"busRouteId": "100100114",
				"busNm": "750A",
				"stId": "120000029",
				"ord": "42",
				"stNm": "서울대학교",
				"arsId": "21128"
			},
			{
				"onoff": "2",
				"from": "서울대학교 관악캠퍼스",
				"to": "숙명여자대학교",
				"from_id": "21128",
				"to_id": "03003",
				"busRouteId": "100100114",
				"busNm": "750A",
				"stId": "102000003",
				"ord": "57",
				"stNm": "신용산역",
				"arsId": "03003"
			}
		],
		[
			{
			},
			{
			}
		],
		[
			{
				"onoff": "1",
				"from": "서울대학교 관악캠퍼스",
				"to": "숙명여자대학교",
				"from_id": "21128",
				"to_id": "03003",
				"busRouteId": "100100565",
				"busNm": "750B",
				"stId": "120000029",
				"ord": "39",
				"stNm": "서울대학교",
				"arsId": "21128"
			},
			{
				"onoff": "2",
				"from": "서울대학교 관악캠퍼스",
				"to": "숙명여자대학교",
				"from_id": "21128",
				"to_id": "03003",
				"busRouteId": "100100565",
				"busNm": "750B",
				"stId": "102000003",
				"ord": "54",
				"stNm": "신용산역",
				"arsId": "03003"
			}
		],
		[
			{
			},
			{
			}
		],
		[
			{
				"onoff": "1",
				"from": "서울대학교 관악캠퍼스",
				"to": "숙명여자대학교",
				"from_id": "21128",
				"to_id": "03009",
				"busRouteId": "100100077",
				"busNm": "501",
				"stId": "120000029",
				"ord": "4",
				"stNm": "서울대학교",
				"arsId": "21128"
			},
			{
				"onoff": "2",
				"from": "서울대학교 관악캠퍼스",
				"to": "숙명여자대학교",
				"from_id": "21128",
				"to_id": "03009",
				"busRouteId": "100100077",
				"busNm": "501",
				"stId": "102000009",
				"ord": "22",
				"stNm": "숙대입구역",
				"arsId": "03009"
			}
		],
		[
			{
				"onoff": "1",
				"from": "서울대학교 관악캠퍼스",
				"to": "숙명여자대학교",
				"from_id": "03230",
				"to_id": "03128",
				"busRouteId": "100100078",
				"busNm": "503",
				"stId": "102000136",
				"ord": "42",
				"stNm": "남영역",
				"arsId": "03230"
			},
			{
				"onoff": "2",
				"from": "서울대학교 관악캠퍼스",
				"to": "숙명여자대학교",
				"from_id": "03230",
				"to_id": "03128",
				"busRouteId": "100100078",
				"busNm": "503",
				"stId": "102000034",
				"ord": "43",
				"stNm": "숙대입구역.청파동주민센터",
				"arsId": "03128"
			}
		],
		[
			{
				"onoff": "1",
				"from": "서울대학교 관악캠퍼스",
				"to": "숙명여자대학교",
				"from_id": "21128",
				"to_id": "03009",
				"busRouteId": "100100077",
				"busNm": "501",
				"stId": "120000029",
				"ord": "4",
				"stNm": "서울대학교",
				"arsId": "21128"
			},
			{
				"onoff": "2",
				"from": "서울대학교 관악캠퍼스",
				"to": "숙명여자대학교",
				"from_id": "21128",
				"to_id": "03009",
				"busRouteId": "100100077",
				"busNm": "501",
				"stId": "102000009",
				"ord": "22",
				"stNm": "숙대입구역",
				"arsId": "03009"
			}
		],
		[
			{
				"onoff": "1",
				"from": "서울대학교 관악캠퍼스",
				"to": "숙명여자대학교",
				"from_id": "03230",
				"to_id": "03128",
				"busRouteId": "100100044",
				"busNm": "262",
				"stId": "102000136",
				"ord": "87",
				"stNm": "남영역",
				"arsId": "03230"
			},
			{
				"onoff": "2",
				"from": "서울대학교 관악캠퍼스",
				"to": "숙명여자대학교",
				"from_id": "03230",
				"to_id": "03128",
				"busRouteId": "100100044",
				"busNm": "262",
				"stId": "102000034",
				"ord": "88",
				"stNm": "숙대입구역.청파동주민센터",
				"arsId": "03128"
			}
		]
	]
}