{
	"resultList": [
		[
			{
			},
			{
			}
		],
		[
			{
				"onoff": "1",
				"from": "삼육대학교",
				"to": "세종대학교",
				"from_id": "07286",
				"to_id": "05243",
				"busRouteId": "100100407",
				"busNm": "240",
				"stId": "106000191",
				"ord": "7",
				"stNm": "신내6단지",
				"arsId": "07286"
			},
			{
				"onoff": "2",
				"from": "삼육대학교",
				"to": "세종대학교",
				"from_id": "07286",
				"to_id": "05243",
				"busRouteId": "100100407",
				"busNm": "240",
				"stId": "104000150",
				"ord": "39",
				"stNm": "세종초등학교.세종사이버대학교앞",
				"arsId": "05243"
			}
		],
		[
			{
			},
			{
			}
		],
		[
			{
				"onoff": "1",
				"from": "삼육대학교",
				"to": "세종대학교",
				"from_id": "07297",
				"to_id": "05243",
				"busRouteId": "100100186",
				"busNm": "2012",
				"stId": "106000202",
				"ord": "8",
				"stNm": "봉화산역3번출구",
				"arsId": "07297"
			},
			{
				"onoff": "2",
				"from": "삼육대학교",
				"to": "세종대학교",
				"from_id": "07297",
				"to_id": "05243",
				"busRouteId": "100100186",
				"busNm": "2012",
				"stId": "104000150",
				"ord": "36",
				"stNm": "세종초등학교.세종사이버대학교앞",
				"arsId": "05243"
			}
		],
		[
			{
				"onoff": "1",
				"from": "삼육대학교",
				"to": "세종대학교",
				"from_id": "11155",
				"to_id": "06015",
				"busRouteId": "100100039",
				"busNm": "202",
				"stId": "110000055",
				"ord": "16",
				"stNm": "삼육대앞",
				"arsId": "11155"
			},
			{
				"onoff": "2",
				"from": "삼육대학교",
				"to": "세종대학교",
				"from_id": "11155",
				"to_id": "06015",
				"busRouteId": "100100039",
				"busNm": "202",
				"stId": "105000015",
				"ord": "38",
				"stNm": "청량리역환승센타",
				"arsId": "06015"
			}
		],
		[
			{
				"onoff": "1",
				"from": "삼육대학교",
				"to": "세종대학교",
				"from_id": "06019",
				"to_id": "05227",
				"busRouteId": "100100218",
				"busNm": "3220",
				"stId": "105000446",
				"ord": "45",
				"stNm": "청량리역환승센터",
				"arsId": "06019"
			},
			{
				"onoff": "2",
				"from": "삼육대학교",
				"to": "세종대학교",
				"from_id": "06019",
				"to_id": "05227",
				"busRouteId": "100100218",
				"busNm": "3220",
				"stId": "104000134",
				"ord": "65",
				"stNm": "어린이대공원역.화양천주교회",
				"arsId": "05227"
			}
		]
	]
}